README.md
setup.cfg
setup.py
pystrct/__init__.py
pystrct/pystrct.py
pystrct.egg-info/PKG-INFO
pystrct.egg-info/SOURCES.txt
pystrct.egg-info/dependency_links.txt
pystrct.egg-info/top_level.txt