Metadata-Version: 1.0
Name: pystrct
Version: 0.1
Summary: A binary file's manager in Python 3.
Home-page: https://github.com/btrevizan/pystrct
Author: Bernardo Trevizan
Author-email: trevizanbernardo@gmail.com
License: UNKNOWN
Keywords: struct,file,binary,python
Platform: UNKNOWN
